[{"id": 946081, "created_at": "2019-06-27 10:17:54", "updated_at": "2020-01-14 19:06:42", "name": "Israel #28", "station": "185.191.207.168", "hostname": "il28.nordvpn.com", "load": 26, "status": "online", "locations": [{"id": 123, "created_at": "2017-06-15 14:06:47", "updated_at": "2017-06-15 14:06:47", "latitude": 32.066667, "longitude": 34.766667, "country": {"id": 105, "name": "Israel", "code": "IL", "city": {"id": 3964220, "name": "Tel Aviv", "latitude": 32.066667, "longitude": 34.766667, "dns_name": "tel-aviv", "hub_score": 0}}}], "technologies": [{"id": 1, "name": "IKEv2/IPSec", "identifier": "ikev2", "created_at": "2017-03-21 12:00:24", "updated_at": "2017-09-05 14:20:16", "pivot": {"status": "online"}}, {"id": 3, "name": "OpenVPN UDP", "identifier": "openvpn_udp", "created_at": "2017-05-04 08:03:24", "updated_at": "2017-05-09 19:27:37", "pivot": {"status": "online"}}, {"id": 5, "name": "OpenVPN TCP", "identifier": "openvpn_tcp", "created_at": "2017-05-09 19:28:14", "updated_at": "2017-05-09 19:28:14", "pivot": {"status": "online"}}, {"id": 9, "name": "HTTP Proxy", "identifier": "proxy", "created_at": "2017-05-09 19:29:09", "updated_at": "2017-06-13 14:25:29", "pivot": {"status": "online"}}, {"id": 19, "name": "HTTP CyberSec Proxy", "identifier": "proxy_cybersec", "created_at": "2017-08-22 12:44:49", "updated_at": "2017-08-22 12:44:49", "pivot": {"status": "online"}}, {"id": 21, "name": "HTTP Proxy (SSL)", "identifier": "proxy_ssl", "created_at": "2017-10-02 12:45:14", "updated_at": "2017-10-02 12:45:14", "pivot": {"status": "online"}}, {"id": 23, "name": "HTTP CyberSec Proxy (SSL)", "identifier": "proxy_ssl_cybersec", "created_at": "2017-10-02 12:50:49", "updated_at": "2017-10-02 12:50:49", "pivot": {"status": "online"}}], "groups": [{"id": 11, "created_at": "2017-06-13 13:43:00", "updated_at": "2017-06-13 13:43:00", "title": "Standard VPN", "type": {"id": 3, "created_at": "2017-06-13 13:40:17", "updated_at": "2017-06-13 13:40:23", "title": "Legacy category", "identifier": "legacy_group_category"}}, {"id": 25, "created_at": "2017-10-27 14:40:12", "updated_at": "2017-10-30 08:10:20", "title": "Africa, the Middle East and India", "type": {"id": 5, "created_at": "2017-10-27 14:16:30", "updated_at": "2017-10-27 14:16:30", "title": "Regions", "identifier": "regions"}}], "ips": [{"id": 136558, "created_at": "2019-06-27 10:17:54", "updated_at": "2019-06-27 10:17:54", "server_id": 946081, "ip_id": 65797, "type": "entry", "ip": {"id": 65797, "ip": "185.191.207.168", "version": 4}}]}, {"id": 938588, "created_at": "2019-03-29 06:00:23", "updated_at": "2020-01-14 19:05:29", "name": "Israel #21", "station": "185.191.207.136", "hostname": "il21.nordvpn.com", "load": 26, "status": "online", "locations": [{"id": 123, "created_at": "2017-06-15 14:06:47", "updated_at": "2017-06-15 14:06:47", "latitude": 32.066667, "longitude": 34.766667, "country": {"id": 105, "name": "Israel", "code": "IL", "city": {"id": 3964220, "name": "Tel Aviv", "latitude": 32.066667, "longitude": 34.766667, "dns_name": "tel-aviv", "hub_score": 0}}}], "technologies": [{"id": 1, "name": "IKEv2/IPSec", "identifier": "ikev2", "created_at": "2017-03-21 12:00:24", "updated_at": "2017-09-05 14:20:16", "pivot": {"status": "online"}}, {"id": 3, "name": "OpenVPN UDP", "identifier": "openvpn_udp", "created_at": "2017-05-04 08:03:24", "updated_at": "2017-05-09 19:27:37", "pivot": {"status": "offline"}}, {"id": 5, "name": "OpenVPN TCP", "identifier": "openvpn_tcp", "created_at": "2017-05-09 19:28:14", "updated_at": "2017-05-09 19:28:14", "pivot": {"status": "online"}}, {"id": 9, "name": "HTTP Proxy", "identifier": "proxy", "created_at": "2017-05-09 19:29:09", "updated_at": "2017-06-13 14:25:29", "pivot": {"status": "online"}}, {"id": 19, "name": "HTTP CyberSec Proxy", "identifier": "proxy_cybersec", "created_at": "2017-08-22 12:44:49", "updated_at": "2017-08-22 12:44:49", "pivot": {"status": "online"}}, {"id": 21, "name": "HTTP Proxy (SSL)", "identifier": "proxy_ssl", "created_at": "2017-10-02 12:45:14", "updated_at": "2017-10-02 12:45:14", "pivot": {"status": "online"}}, {"id": 23, "name": "HTTP CyberSec Proxy (SSL)", "identifier": "proxy_ssl_cybersec", "created_at": "2017-10-02 12:50:49", "updated_at": "2017-10-02 12:50:49", "pivot": {"status": "online"}}], "groups": [{"id": 11, "created_at": "2017-06-13 13:43:00", "updated_at": "2017-06-13 13:43:00", "title": "Standard VPN", "type": {"id": 3, "created_at": "2017-06-13 13:40:17", "updated_at": "2017-06-13 13:40:23", "title": "Legacy category", "identifier": "legacy_group_category"}}, {"id": 25, "created_at": "2017-10-27 14:40:12", "updated_at": "2017-10-30 08:10:20", "title": "Africa, the Middle East and India", "type": {"id": 5, "created_at": "2017-10-27 14:16:30", "updated_at": "2017-10-27 14:16:30", "title": "Regions", "identifier": "regions"}}], "ips": [{"id": 86297, "created_at": "2019-03-29 06:00:23", "updated_at": "2019-03-29 06:00:23", "server_id": 938588, "ip_id": 44243, "type": "entry", "ip": {"id": 44243, "ip": "185.191.207.136", "version": 4}}]}, {"id": 936785, "created_at": "2019-02-26 10:14:54", "updated_at": "2020-01-14 19:05:15", "name": "Israel #17", "station": "185.191.207.56", "hostname": "il17.nordvpn.com", "load": 28, "status": "online", "locations": [{"id": 123, "created_at": "2017-06-15 14:06:47", "updated_at": "2017-06-15 14:06:47", "latitude": 32.066667, "longitude": 34.766667, "country": {"id": 105, "name": "Israel", "code": "IL", "city": {"id": 3964220, "name": "Tel Aviv", "latitude": 32.066667, "longitude": 34.766667, "dns_name": "tel-aviv", "hub_score": 0}}}], "technologies": [{"id": 1, "name": "IKEv2/IPSec", "identifier": "ikev2", "created_at": "2017-03-21 12:00:24", "updated_at": "2017-09-05 14:20:16", "pivot": {"status": "online"}}, {"id": 3, "name": "OpenVPN UDP", "identifier": "openvpn_udp", "created_at": "2017-05-04 08:03:24", "updated_at": "2017-05-09 19:27:37", "pivot": {"status": "online"}}, {"id": 5, "name": "OpenVPN TCP", "identifier": "openvpn_tcp", "created_at": "2017-05-09 19:28:14", "updated_at": "2017-05-09 19:28:14", "pivot": {"status": "online"}}, {"id": 9, "name": "HTTP Proxy", "identifier": "proxy", "created_at": "2017-05-09 19:29:09", "updated_at": "2017-06-13 14:25:29", "pivot": {"status": "online"}}, {"id": 19, "name": "HTTP CyberSec Proxy", "identifier": "proxy_cybersec", "created_at": "2017-08-22 12:44:49", "updated_at": "2017-08-22 12:44:49", "pivot": {"status": "online"}}, {"id": 21, "name": "HTTP Proxy (SSL)", "identifier": "proxy_ssl", "created_at": "2017-10-02 12:45:14", "updated_at": "2017-10-02 12:45:14", "pivot": {"status": "online"}}, {"id": 23, "name": "HTTP CyberSec Proxy (SSL)", "identifier": "proxy_ssl_cybersec", "created_at": "2017-10-02 12:50:49", "updated_at": "2017-10-02 12:50:49", "pivot": {"status": "online"}}], "groups": [{"id": 11, "created_at": "2017-06-13 13:43:00", "updated_at": "2017-06-13 13:43:00", "title": "Standard VPN", "type": {"id": 3, "created_at": "2017-06-13 13:40:17", "updated_at": "2017-06-13 13:40:23", "title": "Legacy category", "identifier": "legacy_group_category"}}, {"id": 25, "created_at": "2017-10-27 14:40:12", "updated_at": "2017-10-30 08:10:20", "title": "Africa, the Middle East and India", "type": {"id": 5, "created_at": "2017-10-27 14:16:30", "updated_at": "2017-10-27 14:16:30", "title": "Regions", "identifier": "regions"}}], "ips": [{"id": 80096, "created_at": "2019-02-26 10:14:54", "updated_at": "2019-02-26 10:14:54", "server_id": 936785, "ip_id": 40706, "type": "entry", "ip": {"id": 40706, "ip": "185.191.207.56", "version": 4}}]}, {"id": 934826, "created_at": "2019-01-16 08:49:55", "updated_at": "2020-01-14 19:04:58", "name": "Israel #14", "station": "185.191.204.131", "hostname": "il14.nordvpn.com", "load": 29, "status": "online", "locations": [{"id": 123, "created_at": "2017-06-15 14:06:47", "updated_at": "2017-06-15 14:06:47", "latitude": 32.066667, "longitude": 34.766667, "country": {"id": 105, "name": "Israel", "code": "IL", "city": {"id": 3964220, "name": "Tel Aviv", "latitude": 32.066667, "longitude": 34.766667, "dns_name": "tel-aviv", "hub_score": 0}}}], "technologies": [{"id": 1, "name": "IKEv2/IPSec", "identifier": "ikev2", "created_at": "2017-03-21 12:00:24", "updated_at": "2017-09-05 14:20:16", "pivot": {"status": "online"}}, {"id": 3, "name": "OpenVPN UDP", "identifier": "openvpn_udp", "created_at": "2017-05-04 08:03:24", "updated_at": "2017-05-09 19:27:37", "pivot": {"status": "online"}}, {"id": 5, "name": "OpenVPN TCP", "identifier": "openvpn_tcp", "created_at": "2017-05-09 19:28:14", "updated_at": "2017-05-09 19:28:14", "pivot": {"status": "online"}}, {"id": 9, "name": "HTTP Proxy", "identifier": "proxy", "created_at": "2017-05-09 19:29:09", "updated_at": "2017-06-13 14:25:29", "pivot": {"status": "online"}}, {"id": 19, "name": "HTTP CyberSec Proxy", "identifier": "proxy_cybersec", "created_at": "2017-08-22 12:44:49", "updated_at": "2017-08-22 12:44:49", "pivot": {"status": "online"}}, {"id": 21, "name": "HTTP Proxy (SSL)", "identifier": "proxy_ssl", "created_at": "2017-10-02 12:45:14", "updated_at": "2017-10-02 12:45:14", "pivot": {"status": "online"}}, {"id": 23, "name": "HTTP CyberSec Proxy (SSL)", "identifier": "proxy_ssl_cybersec", "created_at": "2017-10-02 12:50:49", "updated_at": "2017-10-02 12:50:49", "pivot": {"status": "online"}}], "groups": [{"id": 11, "created_at": "2017-06-13 13:43:00", "updated_at": "2017-06-13 13:43:00", "title": "Standard VPN", "type": {"id": 3, "created_at": "2017-06-13 13:40:17", "updated_at": "2017-06-13 13:40:23", "title": "Legacy category", "identifier": "legacy_group_category"}}, {"id": 25, "created_at": "2017-10-27 14:40:12", "updated_at": "2017-10-30 08:10:20", "title": "Africa, the Middle East and India", "type": {"id": 5, "created_at": "2017-10-27 14:16:30", "updated_at": "2017-10-27 14:16:30", "title": "Regions", "identifier": "regions"}}], "ips": [{"id": 73502, "created_at": "2019-01-16 08:54:23", "updated_at": "2019-01-16 08:54:23", "server_id": 934826, "ip_id": 7847, "type": "entry", "ip": {"id": 7847, "ip": "185.191.204.131", "version": 4}}]}, {"id": 946087, "created_at": "2019-06-27 10:18:35", "updated_at": "2020-01-14 19:06:42", "name": "Israel #30", "station": "185.191.207.178", "hostname": "il30.nordvpn.com", "load": 30, "status": "online", "locations": [{"id": 123, "created_at": "2017-06-15 14:06:47", "updated_at": "2017-06-15 14:06:47", "latitude": 32.066667, "longitude": 34.766667, "country": {"id": 105, "name": "Israel", "code": "IL", "city": {"id": 3964220, "name": "Tel Aviv", "latitude": 32.066667, "longitude": 34.766667, "dns_name": "tel-aviv", "hub_score": 0}}}], "technologies": [{"id": 1, "name": "IKEv2/IPSec", "identifier": "ikev2", "created_at": "2017-03-21 12:00:24", "updated_at": "2017-09-05 14:20:16", "pivot": {"status": "online"}}, {"id": 3, "name": "OpenVPN UDP", "identifier": "openvpn_udp", "created_at": "2017-05-04 08:03:24", "updated_at": "2017-05-09 19:27:37", "pivot": {"status": "online"}}, {"id": 5, "name": "OpenVPN TCP", "identifier": "openvpn_tcp", "created_at": "2017-05-09 19:28:14", "updated_at": "2017-05-09 19:28:14", "pivot": {"status": "online"}}, {"id": 9, "name": "HTTP Proxy", "identifier": "proxy", "created_at": "2017-05-09 19:29:09", "updated_at": "2017-06-13 14:25:29", "pivot": {"status": "online"}}, {"id": 19, "name": "HTTP CyberSec Proxy", "identifier": "proxy_cybersec", "created_at": "2017-08-22 12:44:49", "updated_at": "2017-08-22 12:44:49", "pivot": {"status": "online"}}, {"id": 21, "name": "HTTP Proxy (SSL)", "identifier": "proxy_ssl", "created_at": "2017-10-02 12:45:14", "updated_at": "2017-10-02 12:45:14", "pivot": {"status": "online"}}, {"id": 23, "name": "HTTP CyberSec Proxy (SSL)", "identifier": "proxy_ssl_cybersec", "created_at": "2017-10-02 12:50:49", "updated_at": "2017-10-02 12:50:49", "pivot": {"status": "online"}}], "groups": [{"id": 11, "created_at": "2017-06-13 13:43:00", "updated_at": "2017-06-13 13:43:00", "title": "Standard VPN", "type": {"id": 3, "created_at": "2017-06-13 13:40:17", "updated_at": "2017-06-13 13:40:23", "title": "Legacy category", "identifier": "legacy_group_category"}}, {"id": 25, "created_at": "2017-10-27 14:40:12", "updated_at": "2017-10-30 08:10:20", "title": "Africa, the Middle East and India", "type": {"id": 5, "created_at": "2017-10-27 14:16:30", "updated_at": "2017-10-27 14:16:30", "title": "Regions", "identifier": "regions"}}], "ips": [{"id": 136576, "created_at": "2019-06-27 10:18:35", "updated_at": "2019-06-27 10:18:35", "server_id": 946087, "ip_id": 65809, "type": "entry", "ip": {"id": 65809, "ip": "185.191.207.178", "version": 4}}]}]